msp/__init__.py
msp/__main__.py
msp/arrows.py
msp/colormap_picker.py
msp/gui.py
msp/msplotter.py
msp/plot.py
msp/slider_widget.py
msp/spinbox.py
msp/user_input.py
msp/images/Blues.png
msp/images/BuGn.png
msp/images/BuPu.png
msp/images/GnBu.png
msp/images/Greens.png
msp/images/Greys.png
msp/images/MSPlotter_gui.png
msp/images/OrRd.png
msp/images/Oranges.png
msp/images/PuBu.png
msp/images/PuBuGn.png
msp/images/PuRd.png
msp/images/Purples.png
msp/images/RdPu.png
msp/images/Reds.png
msp/images/YlGn.png
msp/images/YlGnBu.png
msp/images/YlOrBr.png
msp/images/YlOrRd.png
msp/images/__init__.py
msp/images/logo.png
msp/tmp_files/__init__.py
msplotter-0.1.37.dist-info/LICENSE
msplotter-0.1.37.dist-info/METADATA
msplotter-0.1.37.dist-info/WHEEL
msplotter-0.1.37.dist-info/entry_points.txt
msplotter-0.1.37.dist-info/top_level.txt
msplotter-0.1.37.dist-info/RECORD
