Metadata-Version: 2.1
Name: msplotter
Version: 0.1.37
Summary: Make a graphical representation of a blastn alignment
Author-email: Ivan Muñoz-Gutierrez <ivan.munoz.gutierrez@gmail.com>
License: BSD 3-Clause License
Project-URL: Homepage, https://github.com/ivanmugu/MSPlotter
Keywords: blast,alignment,graphical representation,DNA sequence,easyfig
Classifier: Programming Language :: Python
Classifier: License :: OSI Approved :: BSD License
Classifier: Intended Audience :: Science/Research
Classifier: Operating System :: OS Independent
Classifier: Topic :: Scientific/Engineering :: Bio-Informatics
Requires-Python: >=3.11
License-File: LICENSE
Requires-Dist: biopython ==1.81
Requires-Dist: customtkinter ==5.1.3
Requires-Dist: matplotlib ==3.7.1
